BenAI/__init__.py
BenAI/dataset_retriever.py
BenAI-0.0.1.dist-info/LICENSE.txt
BenAI-0.0.1.dist-info/METADATA
BenAI-0.0.1.dist-info/WHEEL
BenAI-0.0.1.dist-info/top_level.txt
BenAI-0.0.1.dist-info/RECORD
